Metadata-Version: 2.4
Name: anonyspark
Version: 0.1.0
Summary: PySpark data masking and anonymization utility
Home-page: https://github.com/yourusername/anonyspark
Author: Naga Adithya Kaushik
Author-email: adithyakaushikch@email.com
License: MIT
Classifier: Programming Language :: Python :: 3
Classifier: License :: OSI Approved :: MIT License
Classifier: Operating System :: OS Independent
Requires-Python: >=3.7
Dynamic: requires-python
